quantecon_book_networks/__init__.py
quantecon_book_networks/configure.py
quantecon_book_networks/data-markov-chains-convert.ipynb
quantecon_book_networks/data.py
quantecon_book_networks/input_output.py
quantecon_book_networks/plotting.py
quantecon_book_networks/.ipynb_checkpoints/data-markov-chains-convert-checkpoint.ipynb
quantecon_book_networks/.virtual_documents/data-markov-chains-convert.ipynb
quantecon_book_networks/data/README.md
quantecon_book_networks/data/commercial_aircraft/aircraft_network.gexf
quantecon_book_networks/data/commercial_aircraft/aircraft_network_layout.json
quantecon_book_networks/data/crude_oil/data.csv
quantecon_book_networks/data/crude_oil/regions-iso3c.csv
quantecon_book_networks/data/crude_oil/sankey-diagram-crude-oil-sitc3330-yr2019.png
quantecon_book_networks/data/csv_files/adjacency_matrix.csv
quantecon_book_networks/data/csv_files/forbes-global2000.csv
quantecon_book_networks/data/csv_files/make_114_aus.csv
quantecon_book_networks/data/csv_files/make_15.csv
quantecon_book_networks/data/csv_files/make_71.csv
quantecon_book_networks/data/csv_files/use_114_aus.csv
quantecon_book_networks/data/csv_files/use_15.csv
quantecon_book_networks/data/csv_files/use_71.csv
quantecon_book_networks/data/markov_chains_networks/wb_gdppc.csv
quantecon_book_networks/data/markov_chains_networks/wb_gdppc_wld.csv
quantecon_book_networks-1.5.dist-info/licenses/LICENSE
quantecon_book_networks-1.5.dist-info/WHEEL
quantecon_book_networks-1.5.dist-info/METADATA
quantecon_book_networks-1.5.dist-info/RECORD
