Metadata-Version: 2.4
Name: quantecon_book_networks
Version: 1.5
Summary: Companion package for book-networks
Author-email: QuantEcon Developers <contact@quantecon.org>
Classifier: License :: OSI Approved :: MIT License
License-File: LICENSE
Requires-Dist: numpy
Requires-Dist: scipy
Requires-Dist: pandas
Requires-Dist: matplotlib
Requires-Dist: networkx
Requires-Dist: wbgapi
Project-URL: Home, https://github.com/quantecon/book-networks
